{
  "name": "iconic-svg",
  "repository": "littlebitselectronics/iconic-svg",
  "version": "0.0.1",
  "main": "index.js",
  "scripts":[
    "index.js"
  ],
  "files": [
    "svg-smart/account.svg",
    "svg-smart/action.svg",
    "svg-smart/align.svg",
    "svg-smart/aperture.svg",
    "svg-smart/arrow-right-angle-thick.svg",
    "svg-smart/arrow-right-angle.svg",
    "svg-smart/arrow-thick.svg",
    "svg-smart/arrow.svg",
    "svg-smart/audio-spectrum.svg",
    "svg-smart/audio.svg",
    "svg-smart/ban.svg",
    "svg-smart/bar-chart.svg",
    "svg-smart/basket.svg",
    "svg-smart/battery.svg",
    "svg-smart/beaker.svg",
    "svg-smart/bell.svg",
    "svg-smart/bitcoin-address.svg",
    "svg-smart/bitcoin-block.svg",
    "svg-smart/bitcoin-transaction.svg",
    "svg-smart/bitcoin.svg",
    "svg-smart/bluetooth.svg",
    "svg-smart/bold.svg",
    "svg-smart/book.svg",
    "svg-smart/bookmark.svg",
    "svg-smart/box.svg",
    "svg-smart/brain.svg",
    "svg-smart/briefcase.svg",
    "svg-smart/british-pound.svg",
    "svg-smart/browser.svg",
    "svg-smart/brush.svg",
    "svg-smart/bug.svg",
    "svg-smart/bullhorn.svg",
    "svg-smart/calculator.svg",
    "svg-smart/calendar.svg",
    "svg-smart/camera-rangefinder.svg",
    "svg-smart/camera-slr.svg",
    "svg-smart/caret.svg",
    "svg-smart/cart.svg",
    "svg-smart/chat.svg",
    "svg-smart/check.svg",
    "svg-smart/chevron.svg",
    "svg-smart/circle-check.svg",
    "svg-smart/circle-x.svg",
    "svg-smart/clipboard.svg",
    "svg-smart/clock.svg",
    "svg-smart/cloud-transfer.svg",
    "svg-smart/cloud.svg",
    "svg-smart/cloudy.svg",
    "svg-smart/code.svg",
    "svg-smart/cog.svg",
    "svg-smart/cogs.svg",
    "svg-smart/collapse.svg",
    "svg-smart/comment-square.svg",
    "svg-smart/compass.svg",
    "svg-smart/contrast.svg",
    "svg-smart/copywriting.svg",
    "svg-smart/credit-card.svg",
    "svg-smart/crop.svg",
    "svg-smart/dashboard.svg",
    "svg-smart/data-transfer.svg",
    "svg-smart/delete.svg",
    "svg-smart/dial.svg",
    "svg-smart/document.svg",
    "svg-smart/dollar.svg",
    "svg-smart/double-quote-sans.svg",
    "svg-smart/double-quote-serif.svg",
    "svg-smart/eject.svg",
    "svg-smart/electric.svg",
    "svg-smart/elevator.svg",
    "svg-smart/ellipses.svg",
    "svg-smart/envelope.svg",
    "svg-smart/euro.svg",
    "svg-smart/excerpt.svg",
    "svg-smart/expand.svg",
    "svg-smart/external-link.svg",
    "svg-smart/eye.svg",
    "svg-smart/eyedropper.svg",
    "svg-smart/file.svg",
    "svg-smart/fire.svg",
    "svg-smart/firefly.svg",
    "svg-smart/flag.svg",
    "svg-smart/flash.svg",
    "svg-smart/folder.svg",
    "svg-smart/fork.svg",
    "svg-smart/fullscreen.svg",
    "svg-smart/game-controller.svg",
    "svg-smart/globe.svg",
    "svg-smart/graph.svg",
    "svg-smart/grid.svg",
    "svg-smart/guides.svg",
    "svg-smart/hard-drive.svg",
    "svg-smart/header.svg",
    "svg-smart/headphones.svg",
    "svg-smart/heart.svg",
    "svg-smart/home.svg",
    "svg-smart/image.svg",
    "svg-smart/inbox.svg",
    "svg-smart/infinity.svg",
    "svg-smart/info.svg",
    "svg-smart/iphone.svg",
    "svg-smart/italic.svg",
    "svg-smart/justify.svg",
    "svg-smart/key.svg",
    "svg-smart/keyboard.svg",
    "svg-smart/laptop.svg",
    "svg-smart/layers.svg",
    "svg-smart/lightbulb.svg",
    "svg-smart/lightning-bolt.svg",
    "svg-smart/lightning.svg",
    "svg-smart/link.svg",
    "svg-smart/list-rich.svg",
    "svg-smart/list.svg",
    "svg-smart/location.svg",
    "svg-smart/lock.svg",
    "svg-smart/loop-circular.svg",
    "svg-smart/loop-square.svg",
    "svg-smart/loop.svg",
    "svg-smart/magic-wand.svg",
    "svg-smart/magnifying-glass.svg",
    "svg-smart/map-marker.svg",
    "svg-smart/map.svg",
    "svg-smart/medal.svg",
    "svg-smart/media-play-circle.svg",
    "svg-smart/media-skip.svg",
    "svg-smart/media-step.svg",
    "svg-smart/media.svg",
    "svg-smart/medical-cross.svg",
    "svg-smart/menu.svg",
    "svg-smart/microphone.svg",
    "svg-smart/minus.svg",
    "svg-smart/monitor.svg",
    "svg-smart/moon.svg",
    "svg-smart/move.svg",
    "svg-smart/musical-note.svg",
    "svg-smart/nexus.svg",
    "svg-smart/paperclip.svg",
    "svg-smart/pen.svg",
    "svg-smart/pencil.svg",
    "svg-smart/people.svg",
    "svg-smart/person.svg",
    "svg-smart/pie-chart.svg",
    "svg-smart/pin.svg",
    "svg-smart/plus.svg",
    "svg-smart/power-standby.svg",
    "svg-smart/print.svg",
    "svg-smart/project.svg",
    "svg-smart/pulse.svg",
    "svg-smart/puzzle-piece.svg",
    "svg-smart/question-mark.svg",
    "svg-smart/rainy.svg",
    "svg-smart/random.svg",
    "svg-smart/reload.svg",
    "svg-smart/resize.svg",
    "svg-smart/rss-alt.svg",
    "svg-smart/rss.svg",
    "svg-smart/screwdriver.svg",
    "svg-smart/script.svg",
    "svg-smart/settings.svg",
    "svg-smart/share-boxed.svg",
    "svg-smart/share.svg",
    "svg-smart/shield.svg",
    "svg-smart/signal.svg",
    "svg-smart/signpost.svg",
    "svg-smart/sort.svg",
    "svg-smart/spreadsheet.svg",
    "svg-smart/star.svg",
    "svg-smart/sun.svg",
    "svg-smart/tablet.svg",
    "svg-smart/tag.svg",
    "svg-smart/tags.svg",
    "svg-smart/target.svg",
    "svg-smart/task.svg",
    "svg-smart/terminal.svg",
    "svg-smart/text.svg",
    "svg-smart/thermometer.svg",
    "svg-smart/thumb.svg",
    "svg-smart/tiara.svg",
    "svg-smart/timer.svg",
    "svg-smart/tint.svg",
    "svg-smart/tools.svg",
    "svg-smart/transfer.svg",
    "svg-smart/trash.svg",
    "svg-smart/vertical-align.svg",
    "svg-smart/video.svg",
    "svg-smart/volume.svg",
    "svg-smart/warning.svg",
    "svg-smart/wifi.svg",
    "svg-smart/wrench.svg",
    "svg-smart/x.svg",
    "svg-smart/yen.svg"
  ]
}